packaging_legacy/__init__.py
packaging_legacy/version.py
packaging_legacy-23.0.post0.dist-info/LICENSE
packaging_legacy-23.0.post0.dist-info/LICENSE.APACHE
packaging_legacy-23.0.post0.dist-info/LICENSE.BSD
packaging_legacy-23.0.post0.dist-info/METADATA
packaging_legacy-23.0.post0.dist-info/WHEEL
packaging_legacy-23.0.post0.dist-info/top_level.txt
packaging_legacy-23.0.post0.dist-info/RECORD
